honeypots/__init__.py
honeypots/__main__.py
honeypots/base_http_server.py
honeypots/base_server.py
honeypots/dhcp_server.py
honeypots/dns_server.py
honeypots/elastic_server.py
honeypots/ftp_server.py
honeypots/helper.py
honeypots/http_proxy_server.py
honeypots/http_server.py
honeypots/https_server.py
honeypots/imap_server.py
honeypots/ipp_server.py
honeypots/irc_server.py
honeypots/ldap_server.py
honeypots/memcache_server.py
honeypots/mssql_server.py
honeypots/mysql_server.py
honeypots/ntp_server.py
honeypots/oracle_server.py
honeypots/pjl_server.py
honeypots/pop3_server.py
honeypots/postgres_server.py
honeypots/rdp_server.py
honeypots/redis_server.py
honeypots/sip_server.py
honeypots/smb_server.py
honeypots/smtp_server.py
honeypots/sniffer.py
honeypots/snmp_server.py
honeypots/socks5_server.py
honeypots/ssh_server.py
honeypots/telnet_server.py
honeypots/testing.py
honeypots/vnc_server.py
honeypots/data/__init__.py
honeypots/data/dummy_page.html
honeypots/data/home.html
honeypots/data/login.html
honeypots-0.66.dist-info/LICENSE
honeypots-0.66.dist-info/METADATA
honeypots-0.66.dist-info/WHEEL
honeypots-0.66.dist-info/entry_points.txt
honeypots-0.66.dist-info/top_level.txt
honeypots-0.66.dist-info/RECORD
