Metadata-Version: 2.1
Name: honeypots
Version: 0.66
Summary: 30 different honeypots in one package! (dhcp, dns, elastic, ftp, http proxy, https proxy, http, https, imap, ipp, irc, ldap, memcache, mssql, mysql, ntp, oracle, pjl, pop3, postgres, rdp, redis, sip, smb, smtp, snmp, socks5, ssh, telnet, vnc)
Author-email: QeeqBox <gigaqeeq@gmail.com>
License: AGPL-3.0
Project-URL: Homepage, https://github.com/qeeqbox/honeypots
Requires-Python: >=3.8
License-File: LICENSE
Requires-Dist: twisted ==21.7.0
Requires-Dist: psutil ==5.9.0
Requires-Dist: pycryptodome ==3.19.0
Requires-Dist: requests ==2.28.2
Requires-Dist: requests[socks] ==2.28.2
Requires-Dist: impacket ==0.9.24
Requires-Dist: paramiko ==3.1.0
Requires-Dist: scapy
Requires-Dist: service-identity ==21.1.0
Requires-Dist: netifaces ==0.11.0
Provides-Extra: dev
Requires-Dist: dnspython ==2.4.2 ; extra == 'dev'
Requires-Dist: elasticsearch ; extra == 'dev'
Requires-Dist: ldap3 ; extra == 'dev'
Requires-Dist: mysql-connector ; extra == 'dev'
Requires-Dist: pre-commit ; extra == 'dev'
Requires-Dist: pymssql ; extra == 'dev'
Requires-Dist: pytest ; extra == 'dev'
Requires-Dist: pytest-xdist ==3.5.0 ; extra == 'dev'
Requires-Dist: redis ; extra == 'dev'
Requires-Dist: vncdotool ; extra == 'dev'
